{"url": "http://en.wikipedia.org/wiki/Canhotinho", "content": "Canhotinho\nCanhotinho (Little Left-handed) is a city located in the state of Pernambuco, Brazil. Located  at 223\u00a0km away from Recife, capital of the state of Pernambuco. Has an estimated (Ibge 2009) population of 24.381 inhabitants.\n\nEconomy\nThe main economic activities in Canhotinho are based in commerce and agribusiness, especially sugarcane, beans, manioc; and livestock such as cattle, sheep and poultry.\n\nEconomic indicators\nEconomy by Sector\n2006\n\nHealth indicators\n{\"citetype\": \"web\", \"url\": \"http://www2.condepefidem.pe.gov.br/web/condepefidem\", \"title\": \"Governo do Estado de Pernambuco - Welcome\", \"publisher\": \".condepefidem.pe.gov.br\"}\n\nReferences\nCoordinates: 8\u00b052\u203255\u2033S 36\u00b011\u203227\u2033W\ufeff / \ufeff8.88194\u00b0S 36.19083\u00b0W\ufeff / -8.88194; -36.19083\n\n"}