  <page>
    <title>Alfena</title>
    <ns>0</ns>
    <id>20815402</id>
    <revision>
      <id>925953227</id>
      <parentid>915123473</parentid>
      <timestamp>2019-11-13T10:04:16Z</timestamp>
      <contributor>
        <username>Scottm1474</username>
        <id>27236024</id>
      </contributor>
      <minor />
      <comment>typo on &quot;201o&quot; to &quot;2010&quot;</comment>
      <model>wikitext</model>
      <format>text/x-wiki</format>
      <text xml:space="preserve">{{For|the Roman gens|Alfena (gens)}}
{{Infobox Portuguese subdivision
|type = parish
|official_name = Alfena
|image_shield =
|region             = [[Norte Region, Portugal|Norte]]
|metro              = [[Metropolitan Area of Porto|Porto]]
|district           = [[Porto District|Porto]]
|municipality       = [[Valongo]]
|coordinates        = {{coord|41.238|-8.525|type:adm1st_region:PT_dim:50000|display=inline,title}}
|area_total = 15.7
|population_total = 18130
|population_as_of = 2016
|website = http://www.freguesiadealfena.pt
|footnotes =
}}
'''Alfena''' is a [[Portugal|Portuguese]] city and parish in the municipality of [[Valongo]], Portugal. The population in 2010 was 18,130,&lt;ref name=ine&gt;[http://www.ine.pt/ngt_server/attachfileu.jsp?look_parentBoui=165404348&amp;att_display=n&amp;att_download=y Instituto Nacional de Estatística (INE)], Census 2011 results according to the 2013 administrative division of Portugal&lt;/ref&gt; in an area of 15.7&amp;nbsp;km².&lt;ref name=dgt&gt;{{Cite web |url=http://www.dgterritorio.pt/cartografia_e_geodesia/cartografia/carta_administrativa_oficial_de_portugal_caop_/caop__download_/carta_administrativa_oficial_de_portugal___versao_2017__em_vigor_/ |title=Áreas das freguesias, concelhos, distritos e país |access-date=2018-11-05 |archive-url=https://web.archive.org/web/20181105172426/http://www.dgterritorio.pt/cartografia_e_geodesia/cartografia/carta_administrativa_oficial_de_portugal_caop_/caop__download_/carta_administrativa_oficial_de_portugal___versao_2017__em_vigor_/ |archive-date=2018-11-05 |url-status=dead }}&lt;/ref&gt;

==References==
{{Reflist}}

[[Category:Parishes of Valongo]]


{{Porto-geo-stub}}</text>
      <sha1>fupdkcqykpbakp1wkxu2fm3p4vylgvl</sha1>
    </revision>
  </page>
