  <page>
    <title>Chebba</title>
    <ns>0</ns>
    <id>12692311</id>
    <revision>
      <id>937282232</id>
      <parentid>915934811</parentid>
      <timestamp>2020-01-24T01:02:54Z</timestamp>
      <contributor>
        <username>Metalmed</username>
        <id>38057500</id>
      </contributor>
      <comment>/* External links */ Commons cat link</comment>
      <model>wikitext</model>
      <format>text/x-wiki</format>
      <text xml:space="preserve">{{Infobox settlement
&lt;!--See the Table at Infobox Settlement for all fields and descriptions of usage--&gt;
&lt;!-- Basic info  ----------------&gt;
|official_name          =Chebba
|other_name             =
|native_name            =  &lt;!-- for cities whose native name is not in English --&gt;
|nickname               = 
|settlement_type        = &lt;!--For Town or Village (Leave blank for the default City)--&gt;
|motto                  =
&lt;!-- images and maps  -----------&gt;
|image_skyline          = 
|imagesize              = 300px
|image_caption          = 
|image_flag             = 
|flag_size              =
|image_seal             = 
|seal_size              =
|image_shield           = 
|shield_size            =
|image_blank_emblem     =
|blank_emblem_type      =
|blank_emblem_size      =
|image_map              = 
|mapsize                = 
|map_caption            = 
|image_map1             = 
|mapsize1               = 
|map_caption1           = 
|image_dot_map          =
|dot_mapsize            =
|dot_map_caption        =
|dot_x =  |dot_y =
|pushpin_map            = Tunisia&lt;!-- the name of a location map as per http://en.wikipedia.org/wiki/Template:Location_map --&gt;
|pushpin_label_position =bottom
|pushpin_map_caption    =Location in Tunisia
&lt;!-- Location ------------------&gt;
|subdivision_type       = Country
|subdivision_name       = [[Image:Flag of Tunisia.svg|25px]] [[Tunisia]]
|subdivision_type1      = [[Governorates of Tunisia|Governorate]]
|subdivision_name1      = [[Mahdia Governorate]]
|subdivision_type2      = 
|subdivision_name2      = 
|subdivision_type3      = 
|subdivision_name3      = 
|subdivision_type4      = 
|subdivision_name4      =
&lt;!-- Politics -----------------&gt;
|government_footnotes   =
|government_type        =
|leader_title           =
|leader_name            =
|leader_title1          =  &lt;!-- for places with, say, both a mayor and a city manager --&gt;
|leader_name1           =
|leader_title2          =
|leader_name2           =
|leader_title3          =
|leader_name3           =
|leader_title4          =
|leader_name4           =
|established_title      =  &lt;!-- Settled --&gt;
|established_date       = 
|established_title2     =  &lt;!-- Incorporated (town) --&gt;
|established_date2      = 
|established_title3     =  &lt;!-- Incorporated (city) --&gt;
|established_date3      =
&lt;!-- Area    ---------------------&gt;
|area_magnitude         = 
|unit_pref                =Imperial &lt;!--Enter: Imperial, if Imperial (metric) is desired--&gt;
|area_footnotes           =
|area_total_km2           = &lt;!-- ALL fields dealing with a measurements are subject to automatic unit conversion--&gt;
|area_land_km2            = &lt;!--See table @ Template:Infobox Settlement for details on automatic unit conversion--&gt;
|area_water_km2           =
|area_total_sq_mi         =
|area_land_sq_mi          =
|area_water_sq_mi         =
|area_water_percent       =
|area_urban_km2           =
|area_urban_sq_mi         =
|area_metro_km2           =
|area_metro_sq_mi         =
|area_blank1_title        =
|area_blank1_km2          =
|area_blank1_sq_mi        =
&lt;!-- Population   -----------------------&gt;
|population_as_of               =2014
|population_footnotes           =&lt;ref&gt;{{cite web|url=http://www.world-gazetteer.com/wg.php?x=1299713111&amp;men=gcis&amp;lng=en&amp;des=gamelan&amp;geo=-212&amp;srt=epnn&amp;col=abcdefghimoq&amp;msz=1500|title=Tunisia: largest cities and towns and statistics of their population|access-date=2011-03-09|archive-url=https://web.archive.org/web/20110628184548/http://www.world-gazetteer.com/wg.php?x=1299713111&amp;men=gcis&amp;lng=en&amp;des=gamelan&amp;geo=-212&amp;srt=epnn&amp;col=abcdefghimoq&amp;msz=1500#|archive-date=2011-06-28|url-status=dead}} World Gazetteer&lt;/ref&gt;
|population_note                =
|population_total               =22232
|population_density_km2         =
|population_density_sq_mi       =
|population_metro               =
|population_density_metro_km2   =
|population_density_metro_sq_mi =
|population_urban               =
|population_density_urban_km2   =
|population_density_urban_sq_mi =
|population_blank1_title        =Ethnicities
|population_blank1              =
|population_blank2_title        =Religions
|population_blank2              =
|population_density_blank1_km2 =   
|population_density_blank1_sq_mi =
&lt;!-- General information  ---------------&gt;
|timezone               = [[Central European Time|CET]]
|utc_offset             = 1
|timezone_DST           = 
|utc_offset_DST         = 
|coordinates            = {{coord|35|14|14|N|11|06|54|E|region:TN|display=inline}}
|elevation_footnotes    =  &lt;!--for references: use &lt;ref&gt; &lt;/ref&gt; tags--&gt;
|elevation_m            = 
|elevation_ft           =
&lt;!-- Area/postal codes &amp; others --------&gt;
|postal_code_type       =  &lt;!-- enter ZIP code, Postcode, Post code, Postal code... --&gt;
|postal_code            =
|area_code              =
|blank_name             =
|blank_info             =
|blank1_name            =
|blank1_info            =
|website                = 
|footnotes              = 
}}

'''Chebba''' ('''La Chebba''', '''Ash Shabbah''', '''aš-Šābbah''', '''Sheba''') is a small city in the [[Mahdia Governorate]] of [[Tunisia]] in [[North Africa]] on the coast of the [[Mediterranean Sea]].&lt;ref name=&quot;Jacobs&quot;&gt;Jacobs, Daniel and Morris, Peter (2001) ''The rough guide to Tunisia'' Rough Guides, London, [https://books.google.com/books?id=k2By-NdV93AC&amp;q=Chebba+Kaboudia#v=onepage page 235], {{ISBN|1-85828-748-0}}&lt;/ref&gt;

==History==
[[File:Tower-ruin-Bordj-Khadidja.png|thumb|left|225px|Ruined tower of Bordj Khadidja at Ras Kaboudia.]]
The city of Chebba derives its name from the [[headland]] {{Convert|3|km|mi|1}} to the east, which was [[Classical antiquity|classically]] known as Caput Vada (''headland above the shoals'').&lt;ref name=&quot;Hannezo&quot;&gt;Hannezo, G. (1905) [https://books.google.com/books?id=PVJNAAAAYAAJ&amp;pg=RA1-PA135 &quot;Chebba et Ras-Kapoudia: Notes Historique&quot;] ''Bulletin de la Société archéologique de Sousse'' 3(5):&amp;nbsp;pp.&amp;nbsp;135&amp;ndash;140; in French&lt;/ref&gt;&lt;ref&gt;The shoals (Latin ''vada'') refer to the shallows between the headland and the [[Kerkennah Islands]], see Hannezo (1905)&lt;/ref&gt;&lt;ref&gt;In a footnote [[Edward Gibbon|Gibbons]] says ''The Caput Vada of Procopius (where Justinian afterwards founded a city &amp;#151; Da Ædific. l. vi. c.6) is the promontory of Ammon in Strabo, the Brachodes of Ptolemy, the Capaudia of the moderns, a long narrow slip that runs into the sea (Shaw's Travels, p. 111).'' Gibbons, Edward (1854) ''The history of the decline and fall of the Roman empire'' John Murry, London, volume 5 [https://books.google.com/books?id=XrUUAAAAQAAJ&amp;pg=PA105 page 105], {{OCLC|}}&lt;/ref&gt;

The Byzantine general [[Belisarius]] landed here in 533 and went on to inflict a devastating defeat on the [[Vandals]].&lt;ref&gt;Bury, J. B. (John Bagnell) (1923) &quot;Chapter XVII: The Reconquest of Africa&quot; ''History of the Later Roman Empire: From the Death of Theodosius I. to the death of Justinian: Volume 2'' Macmillan, New York, [https://books.google.com/books?id=JxWifqqPtUcC&amp;pg=PA130 page 130], {{OCLC|499411636}}&lt;/ref&gt; The town of Chebba was founded by Justinian about 534 CE after the defeat of the [[Vandals]],&lt;ref name=&quot;Hannezo&quot; /&gt; and named '''Justinianopolis'''.&lt;ref&gt;Guérin, Victor (1862) ''Voyage archéologique dans la Régence de Tunis, Volume 1'' Henri Plon, Paris, [https://books.google.com/books?id=ygp1AAAAMAAJ&amp;pg=PA150 page 150], {{OCLC|	23427230}}; in French&lt;/ref&gt;

The headland (Caput Vada) is now known as Ras Kaboudia&lt;ref name=&quot;Hannezo&quot; /&gt; and is site of the ruins of the ''bordj'' (harbor fortress) of Bordj Khadidja, which was built upon [[Byzantine]] foundations.&lt;ref&gt;Carton, Louis Benjamin Charles (1905) [https://books.google.com/books?id=PVJNAAAAYAAJ&amp;pg=RA1-PA127 &quot;Le Bordj Khadidja (Chebba)&quot;] ''Bulletin de la Société archéologique de Sousse'' 3(5):&amp;nbsp;pp.&amp;nbsp;127&amp;ndash;134; in French&lt;/ref&gt;  The fortress guarded the harbor entrance and was one of a chain of similar forts built by the [[Abbasids]] along the coast of [[North Africa]] in the 8th century.  It was later renamed after Khadija Ben Kalthoum, a poet of the eleventh century, who was born in Chebba.&lt;ref&gt;Sadiqi, Fatima ''et al.'' (2009) ''Women writing Africa: The Northern region'' Feminist Press at The City University of New York, New York, [https://books.google.com/books?ei=-UuTTZ2rAY6ssAOLvrW_Cw&amp;ct=result&amp;id=VWsLAQAAMAAJ&amp;q=Zirids#search_anchor page 89], {{ISBN|978-1-55861-588-5}}&lt;/ref&gt;

==Notes==
{{Reflist}}

==External links==
* [http://www.maplandia.com/tunisia/region-5/mahdia/chebba/ &quot;Chebba Map — Satellite Images of Chebba&quot;] Maplandia World Gazetteer
* {{Commons-inline|Category:Chebba|Chebba}}

{{Clear}}

{{Communes of Tunisia}}

[[Category:Populated places in Mahdia Governorate]]
[[Category:Communes of Tunisia]]</text>
      <sha1>dgnqqtgutt5ri52ksnv3v0zqgxd5bsa</sha1>
    </revision>
  </page>
