  <page>
    <title>Granito</title>
    <ns>0</ns>
    <id>24055249</id>
    <revision>
      <id>771918263</id>
      <parentid>771072746</parentid>
      <timestamp>2017-03-24T07:28:43Z</timestamp>
      <contributor>
        <username>InternetArchiveBot</username>
        <id>27015025</id>
      </contributor>
      <comment>Rescuing 1 sources and tagging 0 as dead. #IABot (v1.3beta3)</comment>
      <model>wikitext</model>
      <format>text/x-wiki</format>
      <text xml:space="preserve">{{Infobox settlement
| name                    = Granito
| native_name             = ''Município de Granito''
| native_name_lang        = &lt;!-- ISO 639-2 code e.g. &quot;fr&quot; for French. If more than one, use {{lang}} instead --&gt;
| settlement_type         = [[Municipalities of Brazil|Municipality]]
| image_skyline           = 
| image_alt               = 
| image_caption           = 
| image_flag              = 
| flag_alt                = 
| image_seal              = 
| seal_alt                = 
| image_shield            = 
| shield_alt              = 
| etymology               = 
| nickname                =  
| motto                   = 
| image_map               = Mapa de Granito (2).png
| map_alt                 = 
| map_caption             = Location of Granito in [[Pernambuco]] 
| pushpin_map             = Brazil
| pushpin_label_position  = bottom
| pushpin_map_alt         = 
| pushpin_map_caption     = Location of Granito in Brazil
| coordinates             = {{coord|07|42|57|S|39|36|54|W|region:BR|display=inline,title}}
| coor_pinpoint           = 
| coordinates_footnotes   = 
|subdivision_type       = [[List of countries|Country]]
|subdivision_type1      = [[Regions of Brazil|Region]]
|subdivision_type2      = [[States of Brazil|State]]
|subdivision_name       = {{flag|Brazil}}
|subdivision_name1      = [[Northeast Region, Brazil|Northeast]]
|subdivision_name2      = [[File:Bandeira de Pernambuco.svg|border|22px]] [[Pernambuco]]
| established_title       = Founded
| established_date        = March 1, 1890
| founder                 = 
| seat_type               = 
| seat                    = 
| government_footnotes    = 
| leader_party            = 
| leader_title            = Mayor
| leader_name             = Antonio Carlos Pereira (PDT, 2013–2016)
|leader_title1          =  &lt;!-- for places with, say, both a mayor and a city manager --&gt;
|leader_name1           = 
| unit_pref               = Metric
&lt;!-- ALL fields with measurements have automatic unit conversion --&gt;
&lt;!-- for references: use &lt;ref&gt; tags --&gt;
| area_footnotes          = 
| area_note               = 
| area_water_percent      = 
| area_rank               = 
| area_blank1_title       = 
| area_blank2_title       = 
&lt;!-- square kilometers --&gt;
| area_total_km2          = 522
| area_land_km2           = 
| area_water_km2          = 
| area_urban_km2          = 
| area_rural_km2          = 
| area_metro_km2          = 
| area_blank1_km2         = 
| area_blank2_km2         = 
&lt;!-- hectares --&gt;
| length_km               = 
| width_km                = 
| dimensions_footnotes    = 
| elevation_footnotes     = 
| elevation_m             = 447
| population_as_of        = 2014 
| population_footnotes    = 
| population_total        = 7,251
| population_density_km2  = auto
| population_note         = 
| population_demonym      = Granitense
| timezone1               = [[Time in Brazil|BRT]]
| utc_offset1             = -3
| timezone1_DST           = 
| utc_offset1_DST         = 
| postal_code_type        = 
| postal_code             = 
| area_code_type          = 
| area_code               = 
| iso_code                = 
| website                 = {{URL|granito.pe.gov.br}}
| footnotes               = 
}}
'''Granito''' (''Granite'') is a city  in the state of [[Pernambuco]], [[Brazil]]. The population in 2009, according with [[Brazilian Institute of Geography and Statistics|IBGE]] was 7,251  inhabitants and the total area is {{convert|522|km2|mi2}}.&lt;ref name=&quot;i&quot;/&gt;

==Geography==

* State - [[Pernambuco]]
* Region - [[Sertão]] Pernambucano
* Boundaries - [[Exu, Pernambuco|Exu]] and [[Moreilândia]]    ('''N''');  [[Parnamirim, Pernambuco|Parnamirim]]    ('''S''');  [[Serrita]]   ('''E''');   [[Bodocó]]   ('''W''').
* Area - 521.86&amp;nbsp;km²
* Elevation - 447 m
* Hidrography - [[Brigida River]]
* Vegetation - [[Caatinga]]
* Clima - [[semi arid]] - ([[Sertão]]) hot
* Annual average temperature - 25.4 c
* Distance to [[Recife]] - 592&amp;nbsp;km

==Economy==

The main economic activities in '''Granito''' are based in [[agribusiness]], especially creation of [[cattle]], [[sheep]],  [[goats]], [[donkeys]], [[chickens]];  and plantations of [[maize|corn]].

===Economic Indicators===
{| class=&quot;wikitable&quot; border=&quot;1&quot;
|-
! Population &lt;ref&gt;http://www.ibge.gov.br/home/estatistica/populacao/estimativa2009/POP2009_DOU.pdf[[Brazilian Institute of Geography and Statistics|IBGE]] Population Granito 2009, page 33&lt;/ref&gt;
! [[GDP]] x(1000 R$).&lt;ref&gt;[http://www.ibge.com.br/home/estatistica/economia/pibmunicipios/2003_2007/tab01.pdf Granito 2007 GDP IBGE page 30] {{webarchive|url=https://web.archive.org/web/20160304001818/http://www.ibge.com.br/home/estatistica/economia/pibmunicipios/2003_2007/tab01.pdf |date=2016-03-04 }}&lt;/ref&gt;
! [[GDP per capita|GDP pc]] (R$)
! [[Pernambuco|PE]]
|-
| 6.944
| 19.682
| 2.985
| 0.033%
|-
|}
'''Economy by Sector'''
2006
{| class=&quot;wikitable&quot; border=&quot;1&quot;
|-
! [[Primary sector]] 
! [[Secondary sector]]
! [[Service sector]] 
|-
| 16.28%
|  7.69%
| 76.03%
|-
|}

===Health Indicators===
&lt;ref&gt;[http://www2.condepefidem.pe.gov.br/web/condepefidem PE State site - City by city profile]&lt;/ref&gt;
{| class=&quot;wikitable&quot; border=&quot;1&quot;
|-
! [[Human Development Index|HDI]] (2000)
! Hospitals (2007)
! Hospitals beds (2007)
! Children's Mortality every 1000 (2005)
|-
| 0.597
|  1
| 20
| 28.0 
|-
|}

==References==
{{reflist|2|refs=

&lt;ref name=&quot;i&quot;&gt;{{cite web | url = http://cod.ibge.gov.br/3O9I | title = Granito | year = 2015 | publisher = Instituto Brasileiro de Geografia e Estatstica | location = Brasília, Brazil | accessdate = 2015-08-24 | language = Portuguese}}&lt;/ref&gt;

}}

{{Municipalities of Pernambuco}}

{{DEFAULTSORT:Granito}}
[[Category:Municipalities in Pernambuco]]

{{Pernambuco-geo-stub}}</text>
      <sha1>dg5g0d8au88gv1t3rc8ym7d81vlxalx</sha1>
    </revision>
  </page>
