  <page>
    <title>Kosad</title>
    <ns>0</ns>
    <id>23688194</id>
    <revision>
      <id>923435098</id>
      <parentid>855392926</parentid>
      <timestamp>2019-10-28T15:10:02Z</timestamp>
      <contributor>
        <username>Arjayay</username>
        <id>5718152</id>
      </contributor>
      <minor />
      <comment>Rm Indic script as [[WP:NOINDICSCRIPT]]</comment>
      <model>wikitext</model>
      <format>text/x-wiki</format>
      <text xml:space="preserve">{{Use dmy dates|date=August 2018}}
{{Use Indian English|date=August 2018}}
{{Infobox settlement
| name                    = Kosad
| native_name             = 
| native_name_lang        = 
| other_name              = 
| nickname                = 
| settlement_type         = city
| image_skyline           = 
| image_alt               = 
| image_caption           = 
| pushpin_map             = India Gujarat#India
| pushpin_label_position  = right
| pushpin_map_alt         = 
| pushpin_map_caption     = Location in Gujarat, India
| coordinates             = {{coord|21.284416|N|72.876263|E|display=inline,title}}
| subdivision_type        = Country
| subdivision_name        = {{flag|India}}
| subdivision_type1       = [[States and territories of India|State]]
| subdivision_name1       = [[Gujarat]]
| subdivision_type2       = [[List of districts of India|District]]
| subdivision_name2       = [[Surat district|Surat]]
| established_title       = &lt;!-- Established --&gt;
| established_date        = 
| founder                 = 
| named_for               = 
| parts_type              = s
| parts                   = 
| government_type         = 
| governing_body          = 
| unit_pref               = Metric
| area_footnotes          = 
| area_rank               = 
| area_total_km2          = 5
| elevation_footnotes     = 
| elevation_m             = 13
| population_total        = 25778
| population_as_of        = 2001
| population_rank         = 
| population_density_km2  = 16000
| population_demonym      = 
| population_footnotes    = 
| demographics_type1      = Languages
| demographics1_title1    = Official
| demographics1_info1     = [[Gujarati language|Gujarati]], [[Hindi language|Hindi]]
| timezone1               = [[Indian Standard Time|IST]]
| utc_offset1             = +5:30
| postal_code_type        = &lt;!-- [[Postal Index Number|PIN]] --&gt;
| postal_code             = 
| area_code_type          = Telephone code
| area_code               = 0261
| registration_plate      = GJ-5
| blank1_name_sec1        = Nearest city
| blank1_info_sec1        = Amroli
| blank2_name_sec1        = [[Human sex ratio|Sex ratio]]
| blank2_info_sec1        = 664/1000 males [[male|♂]]/[[female|♀]]
| website                 = {{URL|gujaratindia.com}} 
| footnotes               = 
}}

'''Kosad''' is [[city]] and a [[Municipality]] in [[Surat district]] in the [[India]]n [[States and territories of India|state]] of [[Gujarat]].

== Geography == 
The city is located at an average elevation of {{convert|12|m|ft}}.&lt;ref&gt;
{{Cite web
|url=http://www.fallingrain.com/world/IN/9/Kosad.html
|title=Falling Rain Genomics, Inc - Kosad
|accessdate=
}}{{Failed verification | date= November 2011}}&lt;/ref&gt;

==Demographics==
As of the 2001 Indian [[census]],&lt;ref&gt;{{cite web|url=http://www.censusindia.net/results/town.php?stad=A&amp;state5=999|archiveurl=https://web.archive.org/web/20040616075334/http://www.censusindia.net/results/town.php?stad=A&amp;state5=999|archivedate=2004-06-16|title= Census of India 2001: Data from the 2001 Census, including cities, villages and towns  (Provisional)|accessdate=2008-11-01|publisher= Census Commission of India}}&lt;/ref&gt; Kosad had a population of 26,578. Males constitute 52% of the population and females 48%. Kosad has an average literacy rate of 74%, higher than the national average of 59.5%: male literacy is 81%, and female literacy is 63%. In Kosad, 14% of the population is under 6 years of age.

The said City was included In limits of Surat Municipal Corporation w.e.f 14.02.2006.

==Transport==
By road: Kosad is {{convert|9|km|mi}} from Udhana and {{convert|8|km|mi}} from Surat.

By air: Nearest airport is Surat which is {{convert|21|km|mi}} from Kosad.

==References==
{{reflist}}

== See also ==

*[[Surat]]
*[[List of tourist attractions in Surat]]

[[Category:Suburban area of Surat]]
[[Category:Neighbourhoods in Surat]]
[[Category:Cities and towns in Surat district]]


{{Surat-geo-stub}}</text>
      <sha1>l28eqkt5k9z0b65s3inn9vo5s5b7pph</sha1>
    </revision>
  </page>
