  <page>
    <title>Sotunki</title>
    <ns>0</ns>
    <id>14324106</id>
    <revision>
      <id>918462916</id>
      <parentid>840729603</parentid>
      <timestamp>2019-09-28T19:56:38Z</timestamp>
      <contributor>
        <username>Tom.Reding</username>
        <id>9784415</id>
      </contributor>
      <minor />
      <comment>[[:Category:CS1 errors: deprecated parameters]]: migrate 1/1 |dead-url= to |url-status=; minor cleanup; [[WP:GenFixes]] on</comment>
      <model>wikitext</model>
      <format>text/x-wiki</format>
      <text xml:space="preserve">{{Infobox settlement
&lt;!-- See Template:Infobox settlement for additional fields and descriptions --&gt;
| name                    = Sotunki
| native_name             = Sottungsby
| native_name_lang               = sv
| settlement_type                = City District
| image_map               = Vantaa districts-Sotunki.png
| map_caption                    = Location on the map of Vantaa
| population_total        = 641
| population_footnotes           = &lt;ref&gt;{{cite web |url=http://www.vantaa.fi/instancedata/prime_product_julkaisu/vantaa/embeds/vantaawwwstructure/102017_Vaestoraportti_2014.pdf |title=Archived copy |access-date=2015-05-01 |url-status=dead |archive-url=https://web.archive.org/web/20150202134059/http://www.vantaa.fi/instancedata/prime_product_julkaisu/vantaa/embeds/vantaawwwstructure/102017_Vaestoraportti_2014.pdf |archive-date=2015-02-02 |df= }}&lt;/ref&gt;
| population_as_of               = 1.1.2014
| timezone1                      = GMT +2
| postal_code             = 01200, 01260
| postal_code_type               = Postal Code(s)
| coordinates                    = {{coord|60|17|04|N|25|08|30|E|region:FI-18|display=inline,title}}
| website                        = {{URL|http://www.vantaa.fi/frontpage/}}
}}

'''Sotunki''' ({{lang-sv|Sottungsby}}) is a district of the city of [[Vantaa]], [[Finland]]. The district has an area of 13.7 square kilometers and a population of about 641 (as of 2014), making it one of the least densely populated and most rural districts in the city. It is served by its own high school. The valley and farmland in Sotunki are the district's main attractions. The area has been inhabited since the palaeolithic, with three different stone age camp sites identified.

==References==
{{Reflist}}

{{Vantaa}}

[[Category:Districts of Vantaa]]


{{SouthernFinland-geo-stub}}</text>
      <sha1>npetpdezg3l1623xug73qzqy0opl33m</sha1>
    </revision>
  </page>
